README.md
setup.py
jlpipe/__init__.py
jlpipe/base.py
jlpipe/utils.py
jlpipe.egg-info/PKG-INFO
jlpipe.egg-info/SOURCES.txt
jlpipe.egg-info/dependency_links.txt
jlpipe.egg-info/entry_points.txt
jlpipe.egg-info/requires.txt
jlpipe.egg-info/top_level.txt