Metadata-Version: 2.1
Name: jlpipe
Version: 1.1.0
Summary: jlpipe
Home-page: https://github.com/yjmade/jlpipe
Author: Jay Young
Author-email: dev@yjmade.net
License: UNKNOWN
Platform: UNKNOWN
